mischief/__init__.py
mischief/bin/pymischief.py
mischief/pwned.py
mischief-0.1.0.dist-info/entry_points.txt
mischief-0.1.0.dist-info/LICENSE
mischief-0.1.0.dist-info/WHEEL
mischief-0.1.0.dist-info/METADATA
mischief-0.1.0.dist-info/RECORD
